{
  "id": "ff4d0183-9ac5-4ff4-99d6-9c8e1408e5c4",
  "prevId": "3644a386-7472-41e4-9c7c-add359112fd8",
  "version": "7",
  "dialect": "postgresql",
  "tables": {
    "public.banner_areas": {
      "name": "banner_areas",
      "schema": "",
      "columns": {
        "id": {
          "name": "id",
          "type": "serial",
          "primaryKey": true,
          "notNull": true
        },
        "site_id": {
          "name": "site_id",
          "type": "uuid",
          "primaryKey": false,
          "notNull": true
        },
        "area_id": {
          "name": "area_id",
          "type": "varchar(100)",
          "primaryKey": false,
          "notNull": true
        },
        "area_name": {
          "name": "area_name",
          "type": "varchar(255)",
          "primaryKey": false,
          "notNull": true
        },
        "area_desc": {
          "name": "area_desc",
          "type": "text",
          "primaryKey": false,
          "notNull": false
        },
        "display_type": {
          "name": "display_type",
          "type": "varchar(50)",
          "primaryKey": false,
          "notNull": false,
          "default": "'slide'"
        },
        "sort_order": {
          "name": "sort_order",
          "type": "integer",
          "primaryKey": false,
          "notNull": false,
          "default": 0
        },
        "is_active": {
          "name": "is_active",
          "type": "boolean",
          "primaryKey": false,
          "notNull": false,
          "default": true
        },
        "created_at": {
          "name": "created_at",
          "type": "timestamp",
          "primaryKey": false,
          "notNull": true,
          "default": "now()"
        },
        "updated_at": {
          "name": "updated_at",
          "type": "timestamp",
          "primaryKey": false,
          "notNull": true,
          "default": "now()"
        }
      },
      "indexes": {
        "banner_areas_site_area_idx": {
          "name": "banner_areas_site_area_idx",
          "columns": [
            {
              "expression": "site_id",
              "isExpression": false,
              "asc": true,
              "nulls": "last"
            },
            {
              "expression": "area_id",
              "isExpression": false,
              "asc": true,
              "nulls": "last"
            }
          ],
          "isUnique": true,
          "concurrently": false,
          "method": "btree",
          "with": {}
        }
      },
      "foreignKeys": {
        "banner_areas_site_id_sites_id_fk": {
          "name": "banner_areas_site_id_sites_id_fk",
          "tableFrom": "banner_areas",
          "tableTo": "sites",
          "columnsFrom": [
            "site_id"
          ],
          "columnsTo": [
            "id"
          ],
          "onDelete": "cascade",
          "onUpdate": "no action"
        }
      },
      "compositePrimaryKeys": {},
      "uniqueConstraints": {},
      "policies": {},
      "checkConstraints": {},
      "isRLSEnabled": false
    },
    "public.banner_items": {
      "name": "banner_items",
      "schema": "",
      "columns": {
        "id": {
          "name": "id",
          "type": "serial",
          "primaryKey": true,
          "notNull": true
        },
        "area_id": {
          "name": "area_id",
          "type": "integer",
          "primaryKey": false,
          "notNull": true
        },
        "num": {
          "name": "num",
          "type": "integer",
          "primaryKey": false,
          "notNull": true
        },
        "title": {
          "name": "title",
          "type": "varchar(255)",
          "primaryKey": false,
          "notNull": false
        },
        "img_url": {
          "name": "img_url",
          "type": "text",
          "primaryKey": false,
          "notNull": false
        },
        "video_url": {
          "name": "video_url",
          "type": "text",
          "primaryKey": false,
          "notNull": false
        },
        "link_url": {
          "name": "link_url",
          "type": "text",
          "primaryKey": false,
          "notNull": false
        },
        "link_target": {
          "name": "link_target",
          "type": "varchar(20)",
          "primaryKey": false,
          "notNull": false,
          "default": "'_self'"
        },
        "text_content": {
          "name": "text_content",
          "type": "text",
          "primaryKey": false,
          "notNull": false
        },
        "html_content": {
          "name": "html_content",
          "type": "text",
          "primaryKey": false,
          "notNull": false
        },
        "display_type": {
          "name": "display_type",
          "type": "varchar(50)",
          "primaryKey": false,
          "notNull": false
        },
        "sort_order": {
          "name": "sort_order",
          "type": "integer",
          "primaryKey": false,
          "notNull": false,
          "default": 0
        },
        "is_active": {
          "name": "is_active",
          "type": "boolean",
          "primaryKey": false,
          "notNull": false,
          "default": true
        },
        "created_at": {
          "name": "created_at",
          "type": "timestamp",
          "primaryKey": false,
          "notNull": true,
          "default": "now()"
        },
        "updated_at": {
          "name": "updated_at",
          "type": "timestamp",
          "primaryKey": false,
          "notNull": true,
          "default": "now()"
        }
      },
      "indexes": {},
      "foreignKeys": {
        "banner_items_area_id_banner_areas_id_fk": {
          "name": "banner_items_area_id_banner_areas_id_fk",
          "tableFrom": "banner_items",
          "tableTo": "banner_areas",
          "columnsFrom": [
            "area_id"
          ],
          "columnsTo": [
            "id"
          ],
          "onDelete": "cascade",
          "onUpdate": "no action"
        }
      },
      "compositePrimaryKeys": {},
      "uniqueConstraints": {},
      "policies": {},
      "checkConstraints": {},
      "isRLSEnabled": false
    },
    "public.maintenance_messages": {
      "name": "maintenance_messages",
      "schema": "",
      "columns": {
        "id": {
          "name": "id",
          "type": "serial",
          "primaryKey": true,
          "notNull": true
        },
        "maintenance_request_id": {
          "name": "maintenance_request_id",
          "type": "integer",
          "primaryKey": false,
          "notNull": true
        },
        "sender_type": {
          "name": "sender_type",
          "type": "varchar(20)",
          "primaryKey": false,
          "notNull": true
        },
        "sender_name": {
          "name": "sender_name",
          "type": "varchar(100)",
          "primaryKey": false,
          "notNull": true
        },
        "body": {
          "name": "body",
          "type": "text",
          "primaryKey": false,
          "notNull": true
        },
        "attachments": {
          "name": "attachments",
          "type": "jsonb",
          "primaryKey": false,
          "notNull": false,
          "default": "'[]'::jsonb"
        },
        "created_at": {
          "name": "created_at",
          "type": "timestamp",
          "primaryKey": false,
          "notNull": true,
          "default": "now()"
        }
      },
      "indexes": {
        "maintenance_messages_request_idx": {
          "name": "maintenance_messages_request_idx",
          "columns": [
            {
              "expression": "maintenance_request_id",
              "isExpression": false,
              "asc": true,
              "nulls": "last"
            }
          ],
          "isUnique": false,
          "concurrently": false,
          "method": "btree",
          "with": {}
        }
      },
      "foreignKeys": {
        "maintenance_messages_maintenance_request_id_maintenance_requests_id_fk": {
          "name": "maintenance_messages_maintenance_request_id_maintenance_requests_id_fk",
          "tableFrom": "maintenance_messages",
          "tableTo": "maintenance_requests",
          "columnsFrom": [
            "maintenance_request_id"
          ],
          "columnsTo": [
            "id"
          ],
          "onDelete": "cascade",
          "onUpdate": "no action"
        }
      },
      "compositePrimaryKeys": {},
      "uniqueConstraints": {},
      "policies": {},
      "checkConstraints": {},
      "isRLSEnabled": false
    },
    "public.maintenance_requests": {
      "name": "maintenance_requests",
      "schema": "",
      "columns": {
        "id": {
          "name": "id",
          "type": "serial",
          "primaryKey": true,
          "notNull": true
        },
        "site_id": {
          "name": "site_id",
          "type": "uuid",
          "primaryKey": false,
          "notNull": true
        },
        "title": {
          "name": "title",
          "type": "varchar(255)",
          "primaryKey": false,
          "notNull": true
        },
        "description": {
          "name": "description",
          "type": "text",
          "primaryKey": false,
          "notNull": true
        },
        "category": {
          "name": "category",
          "type": "varchar(50)",
          "primaryKey": false,
          "notNull": true,
          "default": "'other'"
        },
        "priority": {
          "name": "priority",
          "type": "maintenance_priority",
          "typeSchema": "public",
          "primaryKey": false,
          "notNull": true,
          "default": "'normal'"
        },
        "status": {
          "name": "status",
          "type": "maintenance_status",
          "typeSchema": "public",
          "primaryKey": false,
          "notNull": true,
          "default": "'pending'"
        },
        "requested_by": {
          "name": "requested_by",
          "type": "jsonb",
          "primaryKey": false,
          "notNull": true,
          "default": "'{}'::jsonb"
        },
        "attachments": {
          "name": "attachments",
          "type": "jsonb",
          "primaryKey": false,
          "notNull": true,
          "default": "'[]'::jsonb"
        },
        "resolved_at": {
          "name": "resolved_at",
          "type": "timestamp",
          "primaryKey": false,
          "notNull": false
        },
        "admin_order_id": {
          "name": "admin_order_id",
          "type": "integer",
          "primaryKey": false,
          "notNull": false
        },
        "sync_status": {
          "name": "sync_status",
          "type": "sync_status",
          "typeSchema": "public",
          "primaryKey": false,
          "notNull": true,
          "default": "'pending'"
        },
        "sync_attempts": {
          "name": "sync_attempts",
          "type": "integer",
          "primaryKey": false,
          "notNull": true,
          "default": 0
        },
        "last_sync_error": {
          "name": "last_sync_error",
          "type": "text",
          "primaryKey": false,
          "notNull": false
        },
        "next_retry_at": {
          "name": "next_retry_at",
          "type": "timestamp",
          "primaryKey": false,
          "notNull": false
        },
        "external_admin_id": {
          "name": "external_admin_id",
          "type": "integer",
          "primaryKey": false,
          "notNull": false
        },
        "synced_at": {
          "name": "synced_at",
          "type": "timestamp",
          "primaryKey": false,
          "notNull": false
        },
        "created_at": {
          "name": "created_at",
          "type": "timestamp",
          "primaryKey": false,
          "notNull": true,
          "default": "now()"
        },
        "updated_at": {
          "name": "updated_at",
          "type": "timestamp",
          "primaryKey": false,
          "notNull": true,
          "default": "now()"
        }
      },
      "indexes": {
        "maintenance_site_idx": {
          "name": "maintenance_site_idx",
          "columns": [
            {
              "expression": "site_id",
              "isExpression": false,
              "asc": true,
              "nulls": "last"
            }
          ],
          "isUnique": false,
          "concurrently": false,
          "method": "btree",
          "with": {}
        },
        "maintenance_sync_idx": {
          "name": "maintenance_sync_idx",
          "columns": [
            {
              "expression": "sync_status",
              "isExpression": false,
              "asc": true,
              "nulls": "last"
            },
            {
              "expression": "next_retry_at",
              "isExpression": false,
              "asc": true,
              "nulls": "last"
            }
          ],
          "isUnique": false,
          "concurrently": false,
          "method": "btree",
          "with": {}
        }
      },
      "foreignKeys": {
        "maintenance_requests_site_id_sites_id_fk": {
          "name": "maintenance_requests_site_id_sites_id_fk",
          "tableFrom": "maintenance_requests",
          "tableTo": "sites",
          "columnsFrom": [
            "site_id"
          ],
          "columnsTo": [
            "id"
          ],
          "onDelete": "cascade",
          "onUpdate": "no action"
        }
      },
      "compositePrimaryKeys": {},
      "uniqueConstraints": {},
      "policies": {},
      "checkConstraints": {},
      "isRLSEnabled": false
    },
    "public.org_skin_purchases": {
      "name": "org_skin_purchases",
      "schema": "",
      "columns": {
        "id": {
          "name": "id",
          "type": "serial",
          "primaryKey": true,
          "notNull": true
        },
        "organization_id": {
          "name": "organization_id",
          "type": "integer",
          "primaryKey": false,
          "notNull": true
        },
        "skin_id": {
          "name": "skin_id",
          "type": "integer",
          "primaryKey": false,
          "notNull": true
        },
        "order_id": {
          "name": "order_id",
          "type": "integer",
          "primaryKey": false,
          "notNull": false
        },
        "purchased_at": {
          "name": "purchased_at",
          "type": "timestamp",
          "primaryKey": false,
          "notNull": false,
          "default": "now()"
        },
        "created_at": {
          "name": "created_at",
          "type": "timestamp",
          "primaryKey": false,
          "notNull": true,
          "default": "now()"
        }
      },
      "indexes": {
        "org_skin_purchases_org_skin_idx": {
          "name": "org_skin_purchases_org_skin_idx",
          "columns": [
            {
              "expression": "organization_id",
              "isExpression": false,
              "asc": true,
              "nulls": "last"
            },
            {
              "expression": "skin_id",
              "isExpression": false,
              "asc": true,
              "nulls": "last"
            }
          ],
          "isUnique": true,
          "concurrently": false,
          "method": "btree",
          "with": {}
        }
      },
      "foreignKeys": {
        "org_skin_purchases_skin_id_web_skins_id_fk": {
          "name": "org_skin_purchases_skin_id_web_skins_id_fk",
          "tableFrom": "org_skin_purchases",
          "tableTo": "web_skins",
          "columnsFrom": [
            "skin_id"
          ],
          "columnsTo": [
            "id"
          ],
          "onDelete": "cascade",
          "onUpdate": "no action"
        }
      },
      "compositePrimaryKeys": {},
      "uniqueConstraints": {},
      "policies": {},
      "checkConstraints": {},
      "isRLSEnabled": false
    },
    "public.reservations": {
      "name": "reservations",
      "schema": "",
      "columns": {
        "id": {
          "name": "id",
          "type": "serial",
          "primaryKey": true,
          "notNull": true
        },
        "site_id": {
          "name": "site_id",
          "type": "uuid",
          "primaryKey": false,
          "notNull": true
        },
        "customer_name": {
          "name": "customer_name",
          "type": "varchar(100)",
          "primaryKey": false,
          "notNull": true
        },
        "customer_phone": {
          "name": "customer_phone",
          "type": "varchar(50)",
          "primaryKey": false,
          "notNull": true
        },
        "customer_email": {
          "name": "customer_email",
          "type": "varchar(200)",
          "primaryKey": false,
          "notNull": false
        },
        "treatment_id": {
          "name": "treatment_id",
          "type": "integer",
          "primaryKey": false,
          "notNull": false
        },
        "treatment_name": {
          "name": "treatment_name",
          "type": "varchar(255)",
          "primaryKey": false,
          "notNull": false
        },
        "reserved_date": {
          "name": "reserved_date",
          "type": "date",
          "primaryKey": false,
          "notNull": true
        },
        "reserved_time": {
          "name": "reserved_time",
          "type": "time",
          "primaryKey": false,
          "notNull": false
        },
        "memo": {
          "name": "memo",
          "type": "text",
          "primaryKey": false,
          "notNull": false
        },
        "status": {
          "name": "status",
          "type": "reservation_status",
          "typeSchema": "public",
          "primaryKey": false,
          "notNull": true,
          "default": "'pending'"
        },
        "admin_memo": {
          "name": "admin_memo",
          "type": "text",
          "primaryKey": false,
          "notNull": false
        },
        "sync_status": {
          "name": "sync_status",
          "type": "sync_status",
          "typeSchema": "public",
          "primaryKey": false,
          "notNull": true,
          "default": "'pending'"
        },
        "sync_attempts": {
          "name": "sync_attempts",
          "type": "integer",
          "primaryKey": false,
          "notNull": true,
          "default": 0
        },
        "last_sync_error": {
          "name": "last_sync_error",
          "type": "text",
          "primaryKey": false,
          "notNull": false
        },
        "next_retry_at": {
          "name": "next_retry_at",
          "type": "timestamp",
          "primaryKey": false,
          "notNull": false
        },
        "external_admin_id": {
          "name": "external_admin_id",
          "type": "integer",
          "primaryKey": false,
          "notNull": false
        },
        "synced_at": {
          "name": "synced_at",
          "type": "timestamp",
          "primaryKey": false,
          "notNull": false
        },
        "created_at": {
          "name": "created_at",
          "type": "timestamp",
          "primaryKey": false,
          "notNull": true,
          "default": "now()"
        },
        "updated_at": {
          "name": "updated_at",
          "type": "timestamp",
          "primaryKey": false,
          "notNull": true,
          "default": "now()"
        }
      },
      "indexes": {
        "reservations_site_idx": {
          "name": "reservations_site_idx",
          "columns": [
            {
              "expression": "site_id",
              "isExpression": false,
              "asc": true,
              "nulls": "last"
            }
          ],
          "isUnique": false,
          "concurrently": false,
          "method": "btree",
          "with": {}
        },
        "reservations_sync_idx": {
          "name": "reservations_sync_idx",
          "columns": [
            {
              "expression": "sync_status",
              "isExpression": false,
              "asc": true,
              "nulls": "last"
            },
            {
              "expression": "next_retry_at",
              "isExpression": false,
              "asc": true,
              "nulls": "last"
            }
          ],
          "isUnique": false,
          "concurrently": false,
          "method": "btree",
          "with": {}
        }
      },
      "foreignKeys": {
        "reservations_site_id_sites_id_fk": {
          "name": "reservations_site_id_sites_id_fk",
          "tableFrom": "reservations",
          "tableTo": "sites",
          "columnsFrom": [
            "site_id"
          ],
          "columnsTo": [
            "id"
          ],
          "onDelete": "cascade",
          "onUpdate": "no action"
        }
      },
      "compositePrimaryKeys": {},
      "uniqueConstraints": {},
      "policies": {},
      "checkConstraints": {},
      "isRLSEnabled": false
    },
    "public.roodim_sync_logs": {
      "name": "roodim_sync_logs",
      "schema": "",
      "columns": {
        "id": {
          "name": "id",
          "type": "serial",
          "primaryKey": true,
          "notNull": true
        },
        "site_id": {
          "name": "site_id",
          "type": "uuid",
          "primaryKey": false,
          "notNull": true
        },
        "entity_type": {
          "name": "entity_type",
          "type": "varchar(50)",
          "primaryKey": false,
          "notNull": true
        },
        "external_id": {
          "name": "external_id",
          "type": "integer",
          "primaryKey": false,
          "notNull": false
        },
        "action": {
          "name": "action",
          "type": "varchar(20)",
          "primaryKey": false,
          "notNull": true
        },
        "status": {
          "name": "status",
          "type": "varchar(20)",
          "primaryKey": false,
          "notNull": true
        },
        "error_message": {
          "name": "error_message",
          "type": "text",
          "primaryKey": false,
          "notNull": false
        },
        "synced_at": {
          "name": "synced_at",
          "type": "timestamp",
          "primaryKey": false,
          "notNull": false
        },
        "created_at": {
          "name": "created_at",
          "type": "timestamp",
          "primaryKey": false,
          "notNull": true,
          "default": "now()"
        }
      },
      "indexes": {
        "roodim_sync_logs_site_idx": {
          "name": "roodim_sync_logs_site_idx",
          "columns": [
            {
              "expression": "site_id",
              "isExpression": false,
              "asc": true,
              "nulls": "last"
            }
          ],
          "isUnique": false,
          "concurrently": false,
          "method": "btree",
          "with": {}
        },
        "roodim_sync_logs_type_idx": {
          "name": "roodim_sync_logs_type_idx",
          "columns": [
            {
              "expression": "entity_type",
              "isExpression": false,
              "asc": true,
              "nulls": "last"
            },
            {
              "expression": "status",
              "isExpression": false,
              "asc": true,
              "nulls": "last"
            }
          ],
          "isUnique": false,
          "concurrently": false,
          "method": "btree",
          "with": {}
        }
      },
      "foreignKeys": {
        "roodim_sync_logs_site_id_sites_id_fk": {
          "name": "roodim_sync_logs_site_id_sites_id_fk",
          "tableFrom": "roodim_sync_logs",
          "tableTo": "sites",
          "columnsFrom": [
            "site_id"
          ],
          "columnsTo": [
            "id"
          ],
          "onDelete": "cascade",
          "onUpdate": "no action"
        }
      },
      "compositePrimaryKeys": {},
      "uniqueConstraints": {},
      "policies": {},
      "checkConstraints": {},
      "isRLSEnabled": false
    },
    "public.site_admins": {
      "name": "site_admins",
      "schema": "",
      "columns": {
        "id": {
          "name": "id",
          "type": "serial",
          "primaryKey": true,
          "notNull": true
        },
        "site_id": {
          "name": "site_id",
          "type": "uuid",
          "primaryKey": false,
          "notNull": true
        },
        "admin_member_id": {
          "name": "admin_member_id",
          "type": "integer",
          "primaryKey": false,
          "notNull": true
        },
        "name": {
          "name": "name",
          "type": "varchar(100)",
          "primaryKey": false,
          "notNull": true
        },
        "role": {
          "name": "role",
          "type": "admin_role",
          "typeSchema": "public",
          "primaryKey": false,
          "notNull": true,
          "default": "'editor'"
        },
        "last_login_at": {
          "name": "last_login_at",
          "type": "timestamp",
          "primaryKey": false,
          "notNull": false
        },
        "created_at": {
          "name": "created_at",
          "type": "timestamp",
          "primaryKey": false,
          "notNull": true,
          "default": "now()"
        }
      },
      "indexes": {},
      "foreignKeys": {
        "site_admins_site_id_sites_id_fk": {
          "name": "site_admins_site_id_sites_id_fk",
          "tableFrom": "site_admins",
          "tableTo": "sites",
          "columnsFrom": [
            "site_id"
          ],
          "columnsTo": [
            "id"
          ],
          "onDelete": "cascade",
          "onUpdate": "no action"
        }
      },
      "compositePrimaryKeys": {},
      "uniqueConstraints": {},
      "policies": {},
      "checkConstraints": {},
      "isRLSEnabled": false
    },
    "public.site_configs": {
      "name": "site_configs",
      "schema": "",
      "columns": {
        "id": {
          "name": "id",
          "type": "serial",
          "primaryKey": true,
          "notNull": true
        },
        "site_id": {
          "name": "site_id",
          "type": "uuid",
          "primaryKey": false,
          "notNull": true
        },
        "section": {
          "name": "section",
          "type": "varchar(64)",
          "primaryKey": false,
          "notNull": true
        },
        "data": {
          "name": "data",
          "type": "jsonb",
          "primaryKey": false,
          "notNull": true,
          "default": "'{}'::jsonb"
        },
        "updated_at": {
          "name": "updated_at",
          "type": "timestamp",
          "primaryKey": false,
          "notNull": true,
          "default": "now()"
        }
      },
      "indexes": {
        "site_configs_site_section_idx": {
          "name": "site_configs_site_section_idx",
          "columns": [
            {
              "expression": "site_id",
              "isExpression": false,
              "asc": true,
              "nulls": "last"
            },
            {
              "expression": "section",
              "isExpression": false,
              "asc": true,
              "nulls": "last"
            }
          ],
          "isUnique": true,
          "concurrently": false,
          "method": "btree",
          "with": {}
        }
      },
      "foreignKeys": {
        "site_configs_site_id_sites_id_fk": {
          "name": "site_configs_site_id_sites_id_fk",
          "tableFrom": "site_configs",
          "tableTo": "sites",
          "columnsFrom": [
            "site_id"
          ],
          "columnsTo": [
            "id"
          ],
          "onDelete": "cascade",
          "onUpdate": "no action"
        }
      },
      "compositePrimaryKeys": {},
      "uniqueConstraints": {},
      "policies": {},
      "checkConstraints": {},
      "isRLSEnabled": false
    },
    "public.site_contents": {
      "name": "site_contents",
      "schema": "",
      "columns": {
        "id": {
          "name": "id",
          "type": "serial",
          "primaryKey": true,
          "notNull": true
        },
        "site_id": {
          "name": "site_id",
          "type": "uuid",
          "primaryKey": false,
          "notNull": true
        },
        "type": {
          "name": "type",
          "type": "varchar(32)",
          "primaryKey": false,
          "notNull": true
        },
        "slug": {
          "name": "slug",
          "type": "varchar(190)",
          "primaryKey": false,
          "notNull": true
        },
        "title": {
          "name": "title",
          "type": "varchar(255)",
          "primaryKey": false,
          "notNull": true
        },
        "summary": {
          "name": "summary",
          "type": "text",
          "primaryKey": false,
          "notNull": false
        },
        "content": {
          "name": "content",
          "type": "text",
          "primaryKey": false,
          "notNull": false
        },
        "thumb_url": {
          "name": "thumb_url",
          "type": "text",
          "primaryKey": false,
          "notNull": false
        },
        "meta_json": {
          "name": "meta_json",
          "type": "jsonb",
          "primaryKey": false,
          "notNull": true,
          "default": "'{}'::jsonb"
        },
        "sort_order": {
          "name": "sort_order",
          "type": "integer",
          "primaryKey": false,
          "notNull": true,
          "default": 0
        },
        "is_visible": {
          "name": "is_visible",
          "type": "boolean",
          "primaryKey": false,
          "notNull": true,
          "default": true
        },
        "start_at": {
          "name": "start_at",
          "type": "timestamp",
          "primaryKey": false,
          "notNull": false
        },
        "end_at": {
          "name": "end_at",
          "type": "timestamp",
          "primaryKey": false,
          "notNull": false
        },
        "created_at": {
          "name": "created_at",
          "type": "timestamp",
          "primaryKey": false,
          "notNull": true,
          "default": "now()"
        },
        "updated_at": {
          "name": "updated_at",
          "type": "timestamp",
          "primaryKey": false,
          "notNull": true,
          "default": "now()"
        }
      },
      "indexes": {
        "site_contents_unique_idx": {
          "name": "site_contents_unique_idx",
          "columns": [
            {
              "expression": "site_id",
              "isExpression": false,
              "asc": true,
              "nulls": "last"
            },
            {
              "expression": "type",
              "isExpression": false,
              "asc": true,
              "nulls": "last"
            },
            {
              "expression": "slug",
              "isExpression": false,
              "asc": true,
              "nulls": "last"
            }
          ],
          "isUnique": true,
          "concurrently": false,
          "method": "btree",
          "with": {}
        },
        "site_contents_type_idx": {
          "name": "site_contents_type_idx",
          "columns": [
            {
              "expression": "site_id",
              "isExpression": false,
              "asc": true,
              "nulls": "last"
            },
            {
              "expression": "type",
              "isExpression": false,
              "asc": true,
              "nulls": "last"
            }
          ],
          "isUnique": false,
          "concurrently": false,
          "method": "btree",
          "with": {}
        }
      },
      "foreignKeys": {
        "site_contents_site_id_sites_id_fk": {
          "name": "site_contents_site_id_sites_id_fk",
          "tableFrom": "site_contents",
          "tableTo": "sites",
          "columnsFrom": [
            "site_id"
          ],
          "columnsTo": [
            "id"
          ],
          "onDelete": "cascade",
          "onUpdate": "no action"
        }
      },
      "compositePrimaryKeys": {},
      "uniqueConstraints": {},
      "policies": {},
      "checkConstraints": {},
      "isRLSEnabled": false
    },
    "public.site_credentials": {
      "name": "site_credentials",
      "schema": "",
      "columns": {
        "id": {
          "name": "id",
          "type": "serial",
          "primaryKey": true,
          "notNull": true
        },
        "site_id": {
          "name": "site_id",
          "type": "uuid",
          "primaryKey": false,
          "notNull": true
        },
        "email": {
          "name": "email",
          "type": "varchar(255)",
          "primaryKey": false,
          "notNull": true
        },
        "password_hash": {
          "name": "password_hash",
          "type": "varchar(255)",
          "primaryKey": false,
          "notNull": true
        },
        "name": {
          "name": "name",
          "type": "varchar(100)",
          "primaryKey": false,
          "notNull": true
        },
        "admin_customer_id": {
          "name": "admin_customer_id",
          "type": "integer",
          "primaryKey": false,
          "notNull": false
        },
        "admin_member_id": {
          "name": "admin_member_id",
          "type": "integer",
          "primaryKey": false,
          "notNull": false
        },
        "is_active": {
          "name": "is_active",
          "type": "boolean",
          "primaryKey": false,
          "notNull": true,
          "default": true
        },
        "last_login_at": {
          "name": "last_login_at",
          "type": "timestamp",
          "primaryKey": false,
          "notNull": false
        },
        "created_at": {
          "name": "created_at",
          "type": "timestamp",
          "primaryKey": false,
          "notNull": true,
          "default": "now()"
        },
        "updated_at": {
          "name": "updated_at",
          "type": "timestamp",
          "primaryKey": false,
          "notNull": true,
          "default": "now()"
        }
      },
      "indexes": {
        "site_credentials_site_email_idx": {
          "name": "site_credentials_site_email_idx",
          "columns": [
            {
              "expression": "site_id",
              "isExpression": false,
              "asc": true,
              "nulls": "last"
            },
            {
              "expression": "email",
              "isExpression": false,
              "asc": true,
              "nulls": "last"
            }
          ],
          "isUnique": true,
          "concurrently": false,
          "method": "btree",
          "with": {}
        }
      },
      "foreignKeys": {
        "site_credentials_site_id_sites_id_fk": {
          "name": "site_credentials_site_id_sites_id_fk",
          "tableFrom": "site_credentials",
          "tableTo": "sites",
          "columnsFrom": [
            "site_id"
          ],
          "columnsTo": [
            "id"
          ],
          "onDelete": "cascade",
          "onUpdate": "no action"
        }
      },
      "compositePrimaryKeys": {},
      "uniqueConstraints": {},
      "policies": {},
      "checkConstraints": {},
      "isRLSEnabled": false
    },
    "public.site_files": {
      "name": "site_files",
      "schema": "",
      "columns": {
        "id": {
          "name": "id",
          "type": "serial",
          "primaryKey": true,
          "notNull": true
        },
        "site_id": {
          "name": "site_id",
          "type": "uuid",
          "primaryKey": false,
          "notNull": true
        },
        "filename": {
          "name": "filename",
          "type": "varchar(255)",
          "primaryKey": false,
          "notNull": true
        },
        "file_path": {
          "name": "file_path",
          "type": "varchar(500)",
          "primaryKey": false,
          "notNull": false
        },
        "file_type": {
          "name": "file_type",
          "type": "varchar(20)",
          "primaryKey": false,
          "notNull": true
        },
        "content": {
          "name": "content",
          "type": "text",
          "primaryKey": false,
          "notNull": false
        },
        "blob_url": {
          "name": "blob_url",
          "type": "varchar(1000)",
          "primaryKey": false,
          "notNull": false
        },
        "file_size": {
          "name": "file_size",
          "type": "integer",
          "primaryKey": false,
          "notNull": false,
          "default": 0
        },
        "is_entry": {
          "name": "is_entry",
          "type": "boolean",
          "primaryKey": false,
          "notNull": false,
          "default": false
        },
        "sort_order": {
          "name": "sort_order",
          "type": "integer",
          "primaryKey": false,
          "notNull": false,
          "default": 0
        },
        "created_at": {
          "name": "created_at",
          "type": "timestamp",
          "primaryKey": false,
          "notNull": true,
          "default": "now()"
        },
        "updated_at": {
          "name": "updated_at",
          "type": "timestamp",
          "primaryKey": false,
          "notNull": true,
          "default": "now()"
        }
      },
      "indexes": {
        "site_files_site_filename_idx": {
          "name": "site_files_site_filename_idx",
          "columns": [
            {
              "expression": "site_id",
              "isExpression": false,
              "asc": true,
              "nulls": "last"
            },
            {
              "expression": "filename",
              "isExpression": false,
              "asc": true,
              "nulls": "last"
            }
          ],
          "isUnique": true,
          "concurrently": false,
          "method": "btree",
          "with": {}
        }
      },
      "foreignKeys": {
        "site_files_site_id_sites_id_fk": {
          "name": "site_files_site_id_sites_id_fk",
          "tableFrom": "site_files",
          "tableTo": "sites",
          "columnsFrom": [
            "site_id"
          ],
          "columnsTo": [
            "id"
          ],
          "onDelete": "cascade",
          "onUpdate": "no action"
        }
      },
      "compositePrimaryKeys": {},
      "uniqueConstraints": {},
      "policies": {},
      "checkConstraints": {},
      "isRLSEnabled": false
    },
    "public.site_info": {
      "name": "site_info",
      "schema": "",
      "columns": {
        "id": {
          "name": "id",
          "type": "serial",
          "primaryKey": true,
          "notNull": true
        },
        "site_id": {
          "name": "site_id",
          "type": "uuid",
          "primaryKey": false,
          "notNull": true
        },
        "title": {
          "name": "title",
          "type": "varchar(255)",
          "primaryKey": false,
          "notNull": false
        },
        "description": {
          "name": "description",
          "type": "text",
          "primaryKey": false,
          "notNull": false
        },
        "phone": {
          "name": "phone",
          "type": "varchar(20)",
          "primaryKey": false,
          "notNull": false
        },
        "email": {
          "name": "email",
          "type": "varchar(255)",
          "primaryKey": false,
          "notNull": false
        },
        "address": {
          "name": "address",
          "type": "varchar(500)",
          "primaryKey": false,
          "notNull": false
        },
        "business_hours": {
          "name": "business_hours",
          "type": "jsonb",
          "primaryKey": false,
          "notNull": true,
          "default": "'{}'::jsonb"
        },
        "services_provided": {
          "name": "services_provided",
          "type": "jsonb",
          "primaryKey": false,
          "notNull": true,
          "default": "'[]'::jsonb"
        },
        "created_at": {
          "name": "created_at",
          "type": "timestamp",
          "primaryKey": false,
          "notNull": true,
          "default": "now()"
        },
        "updated_at": {
          "name": "updated_at",
          "type": "timestamp",
          "primaryKey": false,
          "notNull": true,
          "default": "now()"
        }
      },
      "indexes": {},
      "foreignKeys": {
        "site_info_site_id_sites_id_fk": {
          "name": "site_info_site_id_sites_id_fk",
          "tableFrom": "site_info",
          "tableTo": "sites",
          "columnsFrom": [
            "site_id"
          ],
          "columnsTo": [
            "id"
          ],
          "onDelete": "cascade",
          "onUpdate": "no action"
        }
      },
      "compositePrimaryKeys": {},
      "uniqueConstraints": {
        "site_info_site_id_unique": {
          "name": "site_info_site_id_unique",
          "nullsNotDistinct": false,
          "columns": [
            "site_id"
          ]
        }
      },
      "policies": {},
      "checkConstraints": {},
      "isRLSEnabled": false
    },
    "public.site_menu_items": {
      "name": "site_menu_items",
      "schema": "",
      "columns": {
        "id": {
          "name": "id",
          "type": "serial",
          "primaryKey": true,
          "notNull": true
        },
        "site_id": {
          "name": "site_id",
          "type": "uuid",
          "primaryKey": false,
          "notNull": true
        },
        "menu_type": {
          "name": "menu_type",
          "type": "varchar(20)",
          "primaryKey": false,
          "notNull": true
        },
        "label": {
          "name": "label",
          "type": "varchar(100)",
          "primaryKey": false,
          "notNull": true
        },
        "url": {
          "name": "url",
          "type": "varchar(500)",
          "primaryKey": false,
          "notNull": false
        },
        "icon": {
          "name": "icon",
          "type": "varchar(64)",
          "primaryKey": false,
          "notNull": false
        },
        "sort_order": {
          "name": "sort_order",
          "type": "integer",
          "primaryKey": false,
          "notNull": true,
          "default": 0
        },
        "is_active": {
          "name": "is_active",
          "type": "boolean",
          "primaryKey": false,
          "notNull": true,
          "default": true
        },
        "parent_id": {
          "name": "parent_id",
          "type": "integer",
          "primaryKey": false,
          "notNull": false
        }
      },
      "indexes": {},
      "foreignKeys": {
        "site_menu_items_site_id_sites_id_fk": {
          "name": "site_menu_items_site_id_sites_id_fk",
          "tableFrom": "site_menu_items",
          "tableTo": "sites",
          "columnsFrom": [
            "site_id"
          ],
          "columnsTo": [
            "id"
          ],
          "onDelete": "cascade",
          "onUpdate": "no action"
        }
      },
      "compositePrimaryKeys": {},
      "uniqueConstraints": {},
      "policies": {},
      "checkConstraints": {},
      "isRLSEnabled": false
    },
    "public.site_sections": {
      "name": "site_sections",
      "schema": "",
      "columns": {
        "id": {
          "name": "id",
          "type": "serial",
          "primaryKey": true,
          "notNull": true
        },
        "site_id": {
          "name": "site_id",
          "type": "uuid",
          "primaryKey": false,
          "notNull": true
        },
        "section_key": {
          "name": "section_key",
          "type": "varchar(32)",
          "primaryKey": false,
          "notNull": true
        },
        "sort_order": {
          "name": "sort_order",
          "type": "integer",
          "primaryKey": false,
          "notNull": true,
          "default": 0
        },
        "is_active": {
          "name": "is_active",
          "type": "boolean",
          "primaryKey": false,
          "notNull": true,
          "default": true
        },
        "settings": {
          "name": "settings",
          "type": "jsonb",
          "primaryKey": false,
          "notNull": true,
          "default": "'{}'::jsonb"
        },
        "created_at": {
          "name": "created_at",
          "type": "timestamp",
          "primaryKey": false,
          "notNull": true,
          "default": "now()"
        },
        "updated_at": {
          "name": "updated_at",
          "type": "timestamp",
          "primaryKey": false,
          "notNull": true,
          "default": "now()"
        }
      },
      "indexes": {},
      "foreignKeys": {
        "site_sections_site_id_sites_id_fk": {
          "name": "site_sections_site_id_sites_id_fk",
          "tableFrom": "site_sections",
          "tableTo": "sites",
          "columnsFrom": [
            "site_id"
          ],
          "columnsTo": [
            "id"
          ],
          "onDelete": "cascade",
          "onUpdate": "no action"
        }
      },
      "compositePrimaryKeys": {},
      "uniqueConstraints": {},
      "policies": {},
      "checkConstraints": {},
      "isRLSEnabled": false
    },
    "public.site_services": {
      "name": "site_services",
      "schema": "",
      "columns": {
        "id": {
          "name": "id",
          "type": "serial",
          "primaryKey": true,
          "notNull": true
        },
        "site_id": {
          "name": "site_id",
          "type": "uuid",
          "primaryKey": false,
          "notNull": true
        },
        "name": {
          "name": "name",
          "type": "varchar(255)",
          "primaryKey": false,
          "notNull": true
        },
        "description": {
          "name": "description",
          "type": "text",
          "primaryKey": false,
          "notNull": false
        },
        "price": {
          "name": "price",
          "type": "integer",
          "primaryKey": false,
          "notNull": false
        },
        "category": {
          "name": "category",
          "type": "varchar(100)",
          "primaryKey": false,
          "notNull": false
        },
        "is_active": {
          "name": "is_active",
          "type": "boolean",
          "primaryKey": false,
          "notNull": true,
          "default": true
        },
        "sort_order": {
          "name": "sort_order",
          "type": "integer",
          "primaryKey": false,
          "notNull": true,
          "default": 0
        },
        "created_at": {
          "name": "created_at",
          "type": "timestamp",
          "primaryKey": false,
          "notNull": true,
          "default": "now()"
        },
        "updated_at": {
          "name": "updated_at",
          "type": "timestamp",
          "primaryKey": false,
          "notNull": true,
          "default": "now()"
        }
      },
      "indexes": {
        "site_services_site_idx": {
          "name": "site_services_site_idx",
          "columns": [
            {
              "expression": "site_id",
              "isExpression": false,
              "asc": true,
              "nulls": "last"
            }
          ],
          "isUnique": false,
          "concurrently": false,
          "method": "btree",
          "with": {}
        }
      },
      "foreignKeys": {
        "site_services_site_id_sites_id_fk": {
          "name": "site_services_site_id_sites_id_fk",
          "tableFrom": "site_services",
          "tableTo": "sites",
          "columnsFrom": [
            "site_id"
          ],
          "columnsTo": [
            "id"
          ],
          "onDelete": "cascade",
          "onUpdate": "no action"
        }
      },
      "compositePrimaryKeys": {},
      "uniqueConstraints": {},
      "policies": {},
      "checkConstraints": {},
      "isRLSEnabled": false
    },
    "public.sites": {
      "name": "sites",
      "schema": "",
      "columns": {
        "id": {
          "name": "id",
          "type": "uuid",
          "primaryKey": true,
          "notNull": true,
          "default": "gen_random_uuid()"
        },
        "slug": {
          "name": "slug",
          "type": "varchar(100)",
          "primaryKey": false,
          "notNull": true
        },
        "name": {
          "name": "name",
          "type": "varchar(255)",
          "primaryKey": false,
          "notNull": true
        },
        "custom_domain": {
          "name": "custom_domain",
          "type": "varchar(253)",
          "primaryKey": false,
          "notNull": false
        },
        "template_id": {
          "name": "template_id",
          "type": "varchar(64)",
          "primaryKey": false,
          "notNull": false,
          "default": "'default'"
        },
        "status": {
          "name": "status",
          "type": "site_status",
          "typeSchema": "public",
          "primaryKey": false,
          "notNull": true,
          "default": "'draft'"
        },
        "site_type": {
          "name": "site_type",
          "type": "site_type",
          "typeSchema": "public",
          "primaryKey": false,
          "notNull": true,
          "default": "'standalone'"
        },
        "admin_customer_id": {
          "name": "admin_customer_id",
          "type": "integer",
          "primaryKey": false,
          "notNull": false
        },
        "admin_member_id": {
          "name": "admin_member_id",
          "type": "integer",
          "primaryKey": false,
          "notNull": false
        },
        "admin_organization_id": {
          "name": "admin_organization_id",
          "type": "integer",
          "primaryKey": false,
          "notNull": false
        },
        "skin_id": {
          "name": "skin_id",
          "type": "integer",
          "primaryKey": false,
          "notNull": false
        },
        "skin_applied_at": {
          "name": "skin_applied_at",
          "type": "timestamp",
          "primaryKey": false,
          "notNull": false
        },
        "skin_version": {
          "name": "skin_version",
          "type": "varchar(20)",
          "primaryKey": false,
          "notNull": false
        },
        "created_at": {
          "name": "created_at",
          "type": "timestamp",
          "primaryKey": false,
          "notNull": true,
          "default": "now()"
        },
        "updated_at": {
          "name": "updated_at",
          "type": "timestamp",
          "primaryKey": false,
          "notNull": true,
          "default": "now()"
        }
      },
      "indexes": {},
      "foreignKeys": {},
      "compositePrimaryKeys": {},
      "uniqueConstraints": {
        "sites_slug_unique": {
          "name": "sites_slug_unique",
          "nullsNotDistinct": false,
          "columns": [
            "slug"
          ]
        }
      },
      "policies": {},
      "checkConstraints": {},
      "isRLSEnabled": false
    },
    "public.used_sso_tokens": {
      "name": "used_sso_tokens",
      "schema": "",
      "columns": {
        "jti": {
          "name": "jti",
          "type": "varchar(64)",
          "primaryKey": true,
          "notNull": true
        },
        "used_at": {
          "name": "used_at",
          "type": "timestamp",
          "primaryKey": false,
          "notNull": true,
          "default": "now()"
        },
        "expires_at": {
          "name": "expires_at",
          "type": "timestamp",
          "primaryKey": false,
          "notNull": true
        }
      },
      "indexes": {},
      "foreignKeys": {},
      "compositePrimaryKeys": {},
      "uniqueConstraints": {},
      "policies": {},
      "checkConstraints": {},
      "isRLSEnabled": false
    },
    "public.web_skin_files": {
      "name": "web_skin_files",
      "schema": "",
      "columns": {
        "id": {
          "name": "id",
          "type": "serial",
          "primaryKey": true,
          "notNull": true
        },
        "skin_id": {
          "name": "skin_id",
          "type": "integer",
          "primaryKey": false,
          "notNull": true
        },
        "filename": {
          "name": "filename",
          "type": "varchar(255)",
          "primaryKey": false,
          "notNull": true
        },
        "file_type": {
          "name": "file_type",
          "type": "varchar(20)",
          "primaryKey": false,
          "notNull": true
        },
        "content": {
          "name": "content",
          "type": "text",
          "primaryKey": false,
          "notNull": false
        },
        "file_size": {
          "name": "file_size",
          "type": "integer",
          "primaryKey": false,
          "notNull": false,
          "default": 0
        },
        "is_entry": {
          "name": "is_entry",
          "type": "boolean",
          "primaryKey": false,
          "notNull": false,
          "default": false
        },
        "sort_order": {
          "name": "sort_order",
          "type": "integer",
          "primaryKey": false,
          "notNull": false,
          "default": 0
        },
        "created_at": {
          "name": "created_at",
          "type": "timestamp",
          "primaryKey": false,
          "notNull": true,
          "default": "now()"
        },
        "updated_at": {
          "name": "updated_at",
          "type": "timestamp",
          "primaryKey": false,
          "notNull": true,
          "default": "now()"
        }
      },
      "indexes": {
        "web_skin_files_skin_filename_idx": {
          "name": "web_skin_files_skin_filename_idx",
          "columns": [
            {
              "expression": "skin_id",
              "isExpression": false,
              "asc": true,
              "nulls": "last"
            },
            {
              "expression": "filename",
              "isExpression": false,
              "asc": true,
              "nulls": "last"
            }
          ],
          "isUnique": true,
          "concurrently": false,
          "method": "btree",
          "with": {}
        }
      },
      "foreignKeys": {
        "web_skin_files_skin_id_web_skins_id_fk": {
          "name": "web_skin_files_skin_id_web_skins_id_fk",
          "tableFrom": "web_skin_files",
          "tableTo": "web_skins",
          "columnsFrom": [
            "skin_id"
          ],
          "columnsTo": [
            "id"
          ],
          "onDelete": "cascade",
          "onUpdate": "no action"
        }
      },
      "compositePrimaryKeys": {},
      "uniqueConstraints": {},
      "policies": {},
      "checkConstraints": {},
      "isRLSEnabled": false
    },
    "public.web_skins": {
      "name": "web_skins",
      "schema": "",
      "columns": {
        "id": {
          "name": "id",
          "type": "serial",
          "primaryKey": true,
          "notNull": true
        },
        "product_id": {
          "name": "product_id",
          "type": "integer",
          "primaryKey": false,
          "notNull": false
        },
        "slug": {
          "name": "slug",
          "type": "varchar(100)",
          "primaryKey": false,
          "notNull": true
        },
        "name": {
          "name": "name",
          "type": "varchar(255)",
          "primaryKey": false,
          "notNull": true
        },
        "description": {
          "name": "description",
          "type": "text",
          "primaryKey": false,
          "notNull": false
        },
        "thumbnail_url": {
          "name": "thumbnail_url",
          "type": "varchar(500)",
          "primaryKey": false,
          "notNull": false
        },
        "preview_url": {
          "name": "preview_url",
          "type": "varchar(500)",
          "primaryKey": false,
          "notNull": false
        },
        "version": {
          "name": "version",
          "type": "varchar(20)",
          "primaryKey": false,
          "notNull": false,
          "default": "'1.0.0'"
        },
        "category": {
          "name": "category",
          "type": "varchar(50)",
          "primaryKey": false,
          "notNull": false
        },
        "is_default": {
          "name": "is_default",
          "type": "boolean",
          "primaryKey": false,
          "notNull": false,
          "default": false
        },
        "is_free": {
          "name": "is_free",
          "type": "boolean",
          "primaryKey": false,
          "notNull": false,
          "default": true
        },
        "creator_id": {
          "name": "creator_id",
          "type": "integer",
          "primaryKey": false,
          "notNull": false
        },
        "file_count": {
          "name": "file_count",
          "type": "integer",
          "primaryKey": false,
          "notNull": false,
          "default": 0
        },
        "status": {
          "name": "status",
          "type": "varchar(20)",
          "primaryKey": false,
          "notNull": false,
          "default": "'draft'"
        },
        "created_at": {
          "name": "created_at",
          "type": "timestamp",
          "primaryKey": false,
          "notNull": true,
          "default": "now()"
        },
        "updated_at": {
          "name": "updated_at",
          "type": "timestamp",
          "primaryKey": false,
          "notNull": true,
          "default": "now()"
        }
      },
      "indexes": {},
      "foreignKeys": {},
      "compositePrimaryKeys": {},
      "uniqueConstraints": {
        "web_skins_slug_unique": {
          "name": "web_skins_slug_unique",
          "nullsNotDistinct": false,
          "columns": [
            "slug"
          ]
        }
      },
      "policies": {},
      "checkConstraints": {},
      "isRLSEnabled": false
    },
    "public.workboard_members": {
      "name": "workboard_members",
      "schema": "",
      "columns": {
        "id": {
          "name": "id",
          "type": "serial",
          "primaryKey": true,
          "notNull": true
        },
        "workboard_id": {
          "name": "workboard_id",
          "type": "integer",
          "primaryKey": false,
          "notNull": true
        },
        "site_id": {
          "name": "site_id",
          "type": "uuid",
          "primaryKey": false,
          "notNull": true
        },
        "invited_at": {
          "name": "invited_at",
          "type": "timestamp",
          "primaryKey": false,
          "notNull": true,
          "default": "now()"
        },
        "created_at": {
          "name": "created_at",
          "type": "timestamp",
          "primaryKey": false,
          "notNull": true,
          "default": "now()"
        }
      },
      "indexes": {
        "workboard_members_wb_site_idx": {
          "name": "workboard_members_wb_site_idx",
          "columns": [
            {
              "expression": "workboard_id",
              "isExpression": false,
              "asc": true,
              "nulls": "last"
            },
            {
              "expression": "site_id",
              "isExpression": false,
              "asc": true,
              "nulls": "last"
            }
          ],
          "isUnique": true,
          "concurrently": false,
          "method": "btree",
          "with": {}
        }
      },
      "foreignKeys": {
        "workboard_members_workboard_id_workboards_id_fk": {
          "name": "workboard_members_workboard_id_workboards_id_fk",
          "tableFrom": "workboard_members",
          "tableTo": "workboards",
          "columnsFrom": [
            "workboard_id"
          ],
          "columnsTo": [
            "id"
          ],
          "onDelete": "cascade",
          "onUpdate": "no action"
        },
        "workboard_members_site_id_sites_id_fk": {
          "name": "workboard_members_site_id_sites_id_fk",
          "tableFrom": "workboard_members",
          "tableTo": "sites",
          "columnsFrom": [
            "site_id"
          ],
          "columnsTo": [
            "id"
          ],
          "onDelete": "cascade",
          "onUpdate": "no action"
        }
      },
      "compositePrimaryKeys": {},
      "uniqueConstraints": {},
      "policies": {},
      "checkConstraints": {},
      "isRLSEnabled": false
    },
    "public.workboards": {
      "name": "workboards",
      "schema": "",
      "columns": {
        "id": {
          "name": "id",
          "type": "serial",
          "primaryKey": true,
          "notNull": true
        },
        "name": {
          "name": "name",
          "type": "varchar(255)",
          "primaryKey": false,
          "notNull": true
        },
        "slug": {
          "name": "slug",
          "type": "varchar(100)",
          "primaryKey": false,
          "notNull": true
        },
        "owner_id": {
          "name": "owner_id",
          "type": "integer",
          "primaryKey": false,
          "notNull": false
        },
        "organization_id": {
          "name": "organization_id",
          "type": "integer",
          "primaryKey": false,
          "notNull": false
        },
        "visibility": {
          "name": "visibility",
          "type": "varchar(20)",
          "primaryKey": false,
          "notNull": true,
          "default": "'private'"
        },
        "created_at": {
          "name": "created_at",
          "type": "timestamp",
          "primaryKey": false,
          "notNull": true,
          "default": "now()"
        },
        "updated_at": {
          "name": "updated_at",
          "type": "timestamp",
          "primaryKey": false,
          "notNull": true,
          "default": "now()"
        }
      },
      "indexes": {},
      "foreignKeys": {},
      "compositePrimaryKeys": {},
      "uniqueConstraints": {
        "workboards_slug_unique": {
          "name": "workboards_slug_unique",
          "nullsNotDistinct": false,
          "columns": [
            "slug"
          ]
        }
      },
      "policies": {},
      "checkConstraints": {},
      "isRLSEnabled": false
    }
  },
  "enums": {
    "public.admin_role": {
      "name": "admin_role",
      "schema": "public",
      "values": [
        "owner",
        "editor"
      ]
    },
    "public.maintenance_priority": {
      "name": "maintenance_priority",
      "schema": "public",
      "values": [
        "low",
        "normal",
        "high",
        "urgent"
      ]
    },
    "public.maintenance_status": {
      "name": "maintenance_status",
      "schema": "public",
      "values": [
        "pending",
        "reviewing",
        "working",
        "done",
        "cancelled"
      ]
    },
    "public.reservation_status": {
      "name": "reservation_status",
      "schema": "public",
      "values": [
        "pending",
        "confirmed",
        "cancelled",
        "completed"
      ]
    },
    "public.site_status": {
      "name": "site_status",
      "schema": "public",
      "values": [
        "draft",
        "active",
        "maintenance"
      ]
    },
    "public.site_type": {
      "name": "site_type",
      "schema": "public",
      "values": [
        "standalone",
        "rental",
        "partner",
        "creator"
      ]
    },
    "public.sync_status": {
      "name": "sync_status",
      "schema": "public",
      "values": [
        "pending",
        "synced",
        "failed"
      ]
    }
  },
  "schemas": {},
  "sequences": {},
  "roles": {},
  "policies": {},
  "views": {},
  "_meta": {
    "columns": {},
    "schemas": {},
    "tables": {}
  }
}